stream/__init__.py
stream/api.py
stream/utils.py
stream/classes/cost_model/communication_manager.py
stream/classes/cost_model/cost_model.py
stream/classes/cost_model/memory_manager.py
stream/classes/cost_model/scheduler.py
stream/classes/hardware/architecture/accelerator.py
stream/classes/hardware/architecture/communication_link.py
stream/classes/hardware/architecture/pooling_array.py
stream/classes/hardware/architecture/pooling_unit.py
stream/classes/hardware/architecture/simd_array.py
stream/classes/hardware/architecture/simd_unit.py
stream/classes/hardware/architecture/utils.py
stream/classes/io/onnx/conv.py
stream/classes/io/onnx/default.py
stream/classes/io/onnx/elementwise.py
stream/classes/io/onnx/flatten.py
stream/classes/io/onnx/gemm.py
stream/classes/io/onnx/lpnormalization.py
stream/classes/io/onnx/matmul.py
stream/classes/io/onnx/model.py
stream/classes/io/onnx/pooling.py
stream/classes/io/onnx/reshape.py
stream/classes/io/onnx/simd.py
stream/classes/io/onnx/transpose.py
stream/classes/opt/allocation/genetic_algorithm/fitness_evaluator.py
stream/classes/opt/allocation/genetic_algorithm/genetic_algorithm.py
stream/classes/opt/allocation/genetic_algorithm/statistics_evaluator.py
stream/classes/opt/splitting/splitting.py
stream/classes/stages/CustomSpatialMappingGeneratorStage.py
stream/classes/stages/GenerateCNWorkloadHybridStage.py
stream/classes/stages/InterCoreMappingStage.py
stream/classes/stages/IntraCoreMappingStage.py
stream/classes/stages/LayerSplittingStage.py
stream/classes/stages/ModelParserStage.py
stream/classes/stages/__init__.py
stream/classes/stages/utils.py
stream/classes/workload/communication_node.py
stream/classes/workload/computation_node.py
stream/classes/workload/dnn_workload.py
stream/classes/workload/dummy_node.py
stream/classes/workload/elementwise_node.py
stream/classes/workload/flatten_node.py
stream/classes/workload/lpnormalization_node.py
stream/classes/workload/node.py
stream/classes/workload/onnx_workload.py
stream_dse-0.0.8.dist-info/LICENSE
stream_dse-0.0.8.dist-info/METADATA
stream_dse-0.0.8.dist-info/WHEEL
stream_dse-0.0.8.dist-info/entry_points.txt
stream_dse-0.0.8.dist-info/top_level.txt
stream_dse-0.0.8.dist-info/RECORD
