Metadata-Version: 2.1
Name: stream-dse
Version: 0.0.8
Summary: Stream - Multi-core accelerator design space exploration with layer-fused scheduling
Author-email: Arne Symons <arne.symons@kuleuven.be>, Linyan Mei <linyan.mei@kuleuven.be>
License: BSD 3-Clause License
Project-URL: Homepage, https://github.com/ZigZag-Project/stream
Keywords: stream,multi-core,accelerator,layer-fused,scheduling,zigzag,dse,design-space-exploration,machine-learning,deep-learning,mapping
Classifier: License :: OSI Approved :: BSD License
Classifier: Programming Language :: Python
Requires-Python: >=3.9
License-File: LICENSE
Requires-Dist: zigzag-dse
Requires-Dist: rtree
Requires-Dist: deap
Requires-Dist: brokenaxes
Provides-Extra: dev
Requires-Dist: bumpver ; extra == 'dev'
Requires-Dist: pip-tools ; extra == 'dev'
Requires-Dist: build ; extra == 'dev'
Requires-Dist: twine ; extra == 'dev'
